{"assets":{"B739911BAF0ED32BA416CD8DF8F7ADA5":{"type":"texture","index":7,"url":{"native":"assets\/B77F25F5-7E57-4701-BFA4-C4443A7AF84D.pdf"},"width":1920,"height":1080},"E40B0B022DC84531D9CD197605E78BC9":{"type":"texture","index":1,"url":{"native":"assets\/B77F25F5-7E57-4701-BFA4-C4443A7AF84D.pdf"},"width":393,"height":81},"414F9E7A00D9B99A6E9BD772362F6ECB":{"type":"texture","index":6,"url":{"native":"assets\/B77F25F5-7E57-4701-BFA4-C4443A7AF84D.pdf"},"width":1920,"height":1080},"proud-touched.gif-0.0000-3.8000":{"type":"video","index":0,"url":{"web":"assets\/proud-touched.gif-0.0000-3.8000.gif","native":"assets\/proud-touched.gif-0.0000-3.8000.gif"},"width":498,"height":273},"7D2154E7934F3EE981DE4ADDC30B6EB6":{"type":"texture","index":2,"url":{"native":"assets\/B77F25F5-7E57-4701-BFA4-C4443A7AF84D.pdf"},"width":580,"height":55},"4825ADEFE8CE49D1372BF4AFDD43816A":{"type":"texture","index":3,"url":{"native":"assets\/B77F25F5-7E57-4701-BFA4-C4443A7AF84D.pdf"},"width":1687,"height":628},"B5C29D531702C6ED71B6CCB3349A0F4F":{"type":"texture","index":5,"url":{"native":"assets\/B77F25F5-7E57-4701-BFA4-C4443A7AF84D.pdf"},"width":498,"height":273},"07AF4E67934160F41A8783FD6E0625A8":{"type":"texture","index":0,"url":{"native":"assets\/B77F25F5-7E57-4701-BFA4-C4443A7AF84D.pdf"},"width":1920,"height":1080},"92900A6A426C3D24A999E4DD1B80FF26":{"type":"texture","index":4,"url":{"native":"assets\/B77F25F5-7E57-4701-BFA4-C4443A7AF84D.pdf"},"width":498,"height":273}},"events":[{"effects":[{"beginTime":0,"baseLayer":{"animations":[],"initialState":{"affineTransform":[1,0,0,1,0,0],"masksToBounds":false,"rotation":0,"scale":1,"position":{"pointX":1538.153564453125,"pointY":927.64453125},"width":498,"sublayerTransform":[1,0,0,0,0,1,0,0,0,0,1,0,0,0,0,1],"contentsRect":{"y":0,"x":0,"width":1,"height":1},"opacity":1,"edgeAntialiasingMask":251658240,"height":273,"hidden":false,"anchorPoint":{"pointX":0.5,"pointY":0.5}},"objectID":"E6B36EF7-DDC1-4D00-8345-A22FAF023309","layers":[{"animations":[],"initialState":{"affineTransform":[1,0,0,1,0,0],"masksToBounds":false,"rotation":0,"scale":1,"position":{"pointX":-329.153564453125,"pointY":-251.14453125},"width":498,"sublayerTransform":[1,0,0,0,0,1,0,0,0,0,1,-0.00035007912466775983,0,0,0,1],"contentsRect":{"y":0,"x":0,"width":1,"height":1},"opacity":1,"edgeAntialiasingMask":251658240,"height":273,"hidden":false,"anchorPoint":{"pointX":-0.66095093263679716,"pointY":-0.91994333791208793}},"layers":[{"animations":[{"additive":false,"timeOffset":0,"beginTime":1e-100,"repeatCount":0,"fillMode":"both","duration":0.01,"autoreverses":false,"animations":[{"additive":false,"timeOffset":0,"beginTime":0,"from":{"scalar":true},"repeatCount":0,"fillMode":"both","duration":0.0001,"autoreverses":false,"property":"hidden","to":{"scalar":false},"removedOnCompletion":true},{"additive":false,"timeOffset":0,"beginTime":0.0001,"from":{"scalar":false},"repeatCount":0,"fillMode":"forwards","duration":0.0099000000000000008,"autoreverses":false,"property":"hidden","to":{"scalar":false},"removedOnCompletion":true}],"removedOnCompletion":false}],"layers":[],"texturedRectangle":{"isBackgroundTexture":true,"singleTextureOpacity":1,"textureType":5,"textBaseline":0,"textXHeight":0,"isVerticalText":false},"initialState":{"affineTransform":[1,0,0,1,0,0],"masksToBounds":false,"rotation":0,"scale":1,"position":{"pointX":248.846435546875,"pointY":136.35546875},"width":498,"sublayerTransform":[1,0,0,0,0,1,0,0,0,0,1,0,0,0,0,1],"contentsRect":{"y":0,"x":0,"width":1,"height":1},"opacity":1,"edgeAntialiasingMask":0,"height":273,"hidden":true,"anchorPoint":{"pointX":0.5,"pointY":0.5}},"texture":"92900A6A426C3D24A999E4DD1B80FF26"}]}]},"effects":[{"beginTime":0,"baseLayer":{"animations":[],"initialState":{"affineTransform":[1,0,0,1,0,0],"masksToBounds":false,"rotation":0,"scale":1,"position":{"pointX":1538.153564453125,"pointY":927.64453125},"width":498,"sublayerTransform":[1,0,0,0,0,1,0,0,0,0,1,0,0,0,0,1],"contentsRect":{"y":0,"x":0,"width":1,"height":1},"opacity":1,"edgeAntialiasingMask":251658240,"height":273,"hidden":false,"anchorPoint":{"pointX":0.5,"pointY":0.5}},"objectID":"E6B36EF7-DDC1-4D00-8345-A22FAF023309","layers":[{"animations":[],"layers":[],"texturedRectangle":{"isBackgroundTexture":true,"singleTextureOpacity":1,"textureType":5,"textBaseline":0,"textXHeight":0,"isVerticalText":false},"initialState":{"affineTransform":[1,0,0,1,0,0],"masksToBounds":false,"rotation":0,"scale":1,"position":{"pointX":248.846435546875,"pointY":136.35546875},"width":498,"sublayerTransform":[1,0,0,0,0,1,0,0,0,0,1,0,0,0,0,1],"contentsRect":{"y":0,"x":0,"width":1,"height":1},"opacity":1,"edgeAntialiasingMask":0,"height":273,"hidden":true,"anchorPoint":{"pointX":0.5,"pointY":0.5}},"texture":"92900A6A426C3D24A999E4DD1B80FF26"},{"animations":[],"layers":[],"isVideoLayer":true,"initialState":{"affineTransform":[1,0,0,1,0,0],"masksToBounds":false,"rotation":0,"scale":1,"position":{"pointX":249,"pointY":136.5},"width":498,"sublayerTransform":[1,0,0,0,0,1,0,0,0,0,1,0,0,0,0,1],"contentsRect":{"y":0,"x":0,"width":1,"height":1},"opacity":1,"edgeAntialiasingMask":251658240,"height":273,"hidden":false,"anchorPoint":{"pointX":0.5,"pointY":0.5}},"texture":"B5C29D531702C6ED71B6CCB3349A0F4F"}]},"effects":[],"movie":{"volume":1,"isStreaming":false,"isAudioOnly":false,"endTime":3.7999999523162842,"startTime":0,"asset":"proud-touched.gif-0.0000-3.8000","loopMode":"looping"},"duration":0,"type":"buildIn","attributes":{"direction":0},"name":"renderMovie","objectID":"E6B36EF7-DDC1-4D00-8345-A22FAF023309"}],"duration":0.01,"type":"buildIn","attributes":{"direction":0},"name":"apple:appear","objectID":"E6B36EF7-DDC1-4D00-8345-A22FAF023309"}],"automaticPlay":false,"hyperlinks":[],"accessibility":[{"text":"Our Setup","targetRectangle":{"y":79,"x":99,"width":395.8450003039838,"height":100.53440856933594}},{"text":"Circa September 2019","targetRectangle":{"y":180.44745779037476,"x":98.599999904632568,"width":579.59000000000003,"height":66.404617309570312}},{"text":"Almost no Macs were DEP\/ADE","targetRectangle":{"y":338.52792358398438,"x":147,"width":681.84000000000015,"height":55.656005859375}},{"text":"Prepared via MDS; AD-bound admin accounts","targetRectangle":{"y":389.96232167110429,"x":147,"width":994.12799999999993,"height":100.656005859375}},{"text":"Small amount of MDM-enrolled Macs","targetRectangle":{"y":486.39671975822421,"x":147,"width":801.16799999999989,"height":100.656005859375}},{"text":"Data Transfers\/Backup facilitated by IT at time of new device setup\/re-image","targetRectangle":{"y":582.83111784534412,"x":147,"width":1641.1200000000001,"height":100.656005859375}},{"text":"FileVault discouraged","targetRectangle":{"y":679.26551593246404,"x":147,"width":459.60000000000014,"height":100.656005859375}},{"text":"Munki on-prem","targetRectangle":{"y":775.69991401958396,"x":147,"width":327.31200000000001,"height":100.656005859375}},{"text":"Encouraging users to update at time of setup","targetRectangle":{"y":872.13431210670387,"x":147,"width":968.25599999999986,"height":100.656005859375}}],"baseLayer":{"animations":[],"initialState":{"affineTransform":[1,0,0,1,0,0],"masksToBounds":false,"rotation":0,"scale":1,"position":{"pointX":960,"pointY":540},"width":1920,"sublayerTransform":[1,0,0,0,0,1,0,0,0,0,1,0,0,0,0,1],"contentsRect":{"y":0,"x":0,"width":1,"height":1},"opacity":1,"edgeAntialiasingMask":251658240,"height":1080,"hidden":false,"anchorPoint":{"pointX":0.5,"pointY":0.5}},"layers":[{"animations":[],"initialState":{"affineTransform":[1,0,0,1,0,0],"masksToBounds":false,"rotation":0,"scale":1,"position":{"pointX":960,"pointY":540},"width":1920,"sublayerTransform":[1,0,0,0,0,1,0,0,0,0,1,0,0,0,0,1],"contentsRect":{"y":0,"x":0,"width":1,"height":1},"opacity":1,"edgeAntialiasingMask":251658240,"height":1080,"hidden":false,"anchorPoint":{"pointX":0.5,"pointY":0.5}},"layers":[{"animations":[],"initialState":{"affineTransform":[1,0,0,1,0,0],"masksToBounds":false,"rotation":0,"scale":1,"position":{"pointX":960,"pointY":540},"width":1920,"sublayerTransform":[1,0,0,0,0,1,0,0,0,0,1,0,0,0,0,1],"contentsRect":{"y":0,"x":0,"width":1,"height":1},"opacity":1,"edgeAntialiasingMask":251658240,"height":1080,"hidden":false,"anchorPoint":{"pointX":0.5,"pointY":0.5}},"layers":[{"animations":[],"layers":[],"texturedRectangle":{"isBackgroundTexture":true,"singleTextureOpacity":1,"textureType":1,"textBaseline":0,"textXHeight":0,"isVerticalText":false},"initialState":{"affineTransform":[1,0,0,1,0,0],"masksToBounds":false,"rotation":0,"scale":1,"position":{"pointX":960,"pointY":540},"width":1920,"sublayerTransform":[1,0,0,0,0,1,0,0,0,0,1,0,0,0,0,1],"contentsRect":{"y":0,"x":0,"width":1,"height":1},"opacity":1,"edgeAntialiasingMask":0,"height":1080,"hidden":false,"anchorPoint":{"pointX":0.5,"pointY":0.5}},"texture":"07AF4E67934160F41A8783FD6E0625A8"}]}]},{"animations":[],"initialState":{"affineTransform":[1,0,0,1,0,0],"masksToBounds":false,"rotation":0,"scale":1,"position":{"pointX":960,"pointY":540},"width":1920,"sublayerTransform":[1,0,0,0,0,1,0,0,0,0,1,0,0,0,0,1],"contentsRect":{"y":0,"x":0,"width":1,"height":1},"opacity":1,"edgeAntialiasingMask":251658240,"height":1080,"hidden":false,"anchorPoint":{"pointX":0.5,"pointY":0.5}},"layers":[{"animations":[],"initialState":{"affineTransform":[1,0,0,1,0,0],"masksToBounds":false,"rotation":0,"scale":1,"position":{"pointX":291.50000000000006,"pointY":115.50000000000003},"width":393,"sublayerTransform":[1,0,0,0,0,1,0,0,0,0,1,0,0,0,0,1],"contentsRect":{"y":0,"x":0,"width":1,"height":1},"opacity":1,"edgeAntialiasingMask":251658240,"height":81,"hidden":false,"anchorPoint":{"pointX":0.5,"pointY":0.5}},"layers":[{"animations":[],"layers":[],"texturedRectangle":{"singleTextureOpacity":1,"textXHeight":0.54253086419753083,"textBaseline":0.79123226212866515,"isBackgroundTexture":true,"isVerticalText":false,"textColor":[0.79732686281204224,0.16231453418731689,0.48277956247329712,1],"textureType":6},"initialState":{"affineTransform":[1,0,0,1,0,0],"masksToBounds":false,"rotation":0,"scale":1,"position":{"pointX":202.49999999999994,"pointY":62.499999999999972},"width":393,"sublayerTransform":[1,0,0,0,0,1,0,0,0,0,1,0,0,0,0,1],"contentsRect":{"y":0,"x":0,"width":1,"height":1},"opacity":1,"edgeAntialiasingMask":0,"height":81,"hidden":false,"anchorPoint":{"pointX":0.5,"pointY":0.5}},"texture":"E40B0B022DC84531D9CD197605E78BC9"}]}]},{"animations":[],"initialState":{"affineTransform":[1,0,0,1,0,0],"masksToBounds":false,"rotation":0,"scale":1,"position":{"pointX":960,"pointY":540},"width":1920,"sublayerTransform":[1,0,0,0,0,1,0,0,0,0,1,0,0,0,0,1],"contentsRect":{"y":0,"x":0,"width":1,"height":1},"opacity":1,"edgeAntialiasingMask":251658240,"height":1080,"hidden":false,"anchorPoint":{"pointX":0.5,"pointY":0.5}},"layers":[{"animations":[],"initialState":{"affineTransform":[1,0,0,1,0,0],"masksToBounds":false,"rotation":0,"scale":1,"position":{"pointX":385,"pointY":204.34745788574219},"width":580,"sublayerTransform":[1,0,0,0,0,1,0,0,0,0,1,0,0,0,0,1],"contentsRect":{"y":0,"x":0,"width":1,"height":1},"opacity":1,"edgeAntialiasingMask":251658240,"height":55,"hidden":false,"anchorPoint":{"pointX":0.5,"pointY":0.5}},"layers":[{"animations":[],"layers":[],"texturedRectangle":{"singleTextureOpacity":1,"textXHeight":0.51700000000000002,"textBaseline":0.7803152171048251,"isBackgroundTexture":true,"isVerticalText":false,"textColor":[0,0,0,1],"textureType":6},"initialState":{"affineTransform":[1,0,0,1,0,0],"masksToBounds":false,"rotation":0,"scale":1,"position":{"pointX":294,"pointY":42.652542114257812},"width":580,"sublayerTransform":[1,0,0,0,0,1,0,0,0,0,1,0,0,0,0,1],"contentsRect":{"y":0,"x":0,"width":1,"height":1},"opacity":1,"edgeAntialiasingMask":0,"height":55,"hidden":false,"anchorPoint":{"pointX":0.5,"pointY":0.5}},"texture":"7D2154E7934F3EE981DE4ADDC30B6EB6"}]}]},{"animations":[],"initialState":{"affineTransform":[1,0,0,1,0,0],"masksToBounds":false,"rotation":0,"scale":1,"position":{"pointX":960,"pointY":540},"width":1920,"sublayerTransform":[1,0,0,0,0,1,0,0,0,0,1,0,0,0,0,1],"contentsRect":{"y":0,"x":0,"width":1,"height":1},"opacity":1,"edgeAntialiasingMask":251658240,"height":1080,"hidden":false,"anchorPoint":{"pointX":0.5,"pointY":0.5}},"layers":[{"animations":[],"initialState":{"affineTransform":[1,0,0,1,0,0],"masksToBounds":false,"rotation":0,"scale":1,"position":{"pointX":938.5,"pointY":648.52792358398438},"width":1687,"sublayerTransform":[1,0,0,0,0,1,0,0,0,0,1,0,0,0,0,1],"contentsRect":{"y":0,"x":0,"width":1,"height":1},"opacity":1,"edgeAntialiasingMask":251658240,"height":628,"hidden":false,"anchorPoint":{"pointX":0.5,"pointY":0.5}},"layers":[{"animations":[],"layers":[],"texturedRectangle":{"singleTextureOpacity":1,"textXHeight":0.039515923566878983,"textBaseline":0.98020133919260166,"isBackgroundTexture":true,"isVerticalText":false,"textColor":[0,0,0,1],"textureType":6},"initialState":{"affineTransform":[1,0,0,1,0,0],"masksToBounds":false,"rotation":0,"scale":1,"position":{"pointX":851.5,"pointY":326.47207641601568},"width":1687,"sublayerTransform":[1,0,0,0,0,1,0,0,0,0,1,0,0,0,0,1],"contentsRect":{"y":0,"x":0,"width":1,"height":1},"opacity":1,"edgeAntialiasingMask":0,"height":628,"hidden":false,"anchorPoint":{"pointX":0.5,"pointY":0.5}},"texture":"4825ADEFE8CE49D1372BF4AFDD43816A"}]}]},{"animations":[],"initialState":{"affineTransform":[1,0,0,1,0,0],"masksToBounds":false,"rotation":0,"scale":1,"position":{"pointX":960,"pointY":540},"width":1920,"sublayerTransform":[1,0,0,0,0,1,0,0,0,0,1,0,0,0,0,1],"contentsRect":{"y":0,"x":0,"width":1,"height":1},"opacity":1,"edgeAntialiasingMask":251658240,"height":1080,"hidden":false,"anchorPoint":{"pointX":0.5,"pointY":0.5}},"layers":[{"animations":[],"initialState":{"affineTransform":[1,0,0,1,0,0],"masksToBounds":false,"rotation":0,"scale":1,"position":{"pointX":1538.153564453125,"pointY":927.64453125},"width":498,"sublayerTransform":[1,0,0,0,0,1,0,0,0,0,1,0,0,0,0,1],"contentsRect":{"y":0,"x":0,"width":1,"height":1},"opacity":1,"edgeAntialiasingMask":251658240,"height":273,"hidden":false,"anchorPoint":{"pointX":0.5,"pointY":0.5}},"objectID":"E6B36EF7-DDC1-4D00-8345-A22FAF023309","layers":[{"animations":[],"layers":[],"texturedRectangle":{"isBackgroundTexture":true,"singleTextureOpacity":1,"textureType":5,"textBaseline":0,"textXHeight":0,"isVerticalText":false},"initialState":{"affineTransform":[1,0,0,1,0,0],"masksToBounds":false,"rotation":0,"scale":1,"position":{"pointX":248.846435546875,"pointY":136.35546875},"width":498,"sublayerTransform":[1,0,0,0,0,1,0,0,0,0,1,0,0,0,0,1],"contentsRect":{"y":0,"x":0,"width":1,"height":1},"opacity":1,"edgeAntialiasingMask":0,"height":273,"hidden":true,"anchorPoint":{"pointX":0.5,"pointY":0.5}},"texture":"92900A6A426C3D24A999E4DD1B80FF26"}]}]}]}},{"effects":[{"beginTime":0,"baseLayer":{"animations":[],"initialState":{"affineTransform":[1,0,0,1,0,0],"masksToBounds":false,"rotation":0,"scale":1,"position":{"pointX":960,"pointY":540},"width":1920,"sublayerTransform":[1,0,0,0,0,1,0,0,0,0,1,0,0,0,0,1],"contentsRect":{"y":0,"x":0,"width":1,"height":1},"opacity":1,"edgeAntialiasingMask":251658240,"height":1080,"hidden":false,"anchorPoint":{"pointX":0.5,"pointY":0.5}},"objectID":"0","layers":[{"animations":[],"initialState":{"affineTransform":[1,0,0,1,0,0],"masksToBounds":false,"rotation":0,"scale":1,"position":{"pointX":960,"pointY":540},"width":1920,"sublayerTransform":[1,0,0,0,0,1,0,0,0,0,1,-0.00035007912466775983,0,0,0,1],"contentsRect":{"y":0,"x":0,"width":1,"height":1},"opacity":1,"edgeAntialiasingMask":251658240,"height":1080,"hidden":false,"anchorPoint":{"pointX":0.5,"pointY":0.5}},"layers":[{"animations":[],"layers":[],"texturedRectangle":{"isBackgroundTexture":false,"singleTextureOpacity":1,"textureType":0,"textBaseline":0,"textXHeight":0,"isVerticalText":false},"initialState":{"affineTransform":[1,0,0,1,0,0],"masksToBounds":false,"rotation":0,"scale":1,"position":{"pointX":960,"pointY":540},"width":1920,"sublayerTransform":[1,0,0,0,0,1,0,0,0,0,1,0,0,0,0,1],"contentsRect":{"y":0,"x":0,"width":1,"height":1},"opacity":1,"edgeAntialiasingMask":0,"height":1080,"hidden":false,"anchorPoint":{"pointX":0.5,"pointY":0.5}},"texture":"B739911BAF0ED32BA416CD8DF8F7ADA5"},{"animations":[{"additive":false,"timeOffset":0,"beginTime":0,"from":{"scalar":false},"repeatCount":0,"fillMode":"both","duration":0.001,"autoreverses":false,"property":"hidden","to":{"scalar":true},"removedOnCompletion":false}],"layers":[],"texturedRectangle":{"isBackgroundTexture":false,"singleTextureOpacity":1,"textureType":0,"textBaseline":0,"textXHeight":0,"isVerticalText":false},"initialState":{"affineTransform":[1,0,0,1,0,0],"masksToBounds":false,"rotation":0,"scale":1,"position":{"pointX":960,"pointY":540},"width":1920,"sublayerTransform":[1,0,0,0,0,1,0,0,0,0,1,0,0,0,0,1],"contentsRect":{"y":0,"x":0,"width":1,"height":1},"opacity":1,"edgeAntialiasingMask":0,"height":1080,"hidden":false,"anchorPoint":{"pointX":0.5,"pointY":0.5}},"texture":"414F9E7A00D9B99A6E9BD772362F6ECB"}]}]},"effects":[],"duration":0.001,"type":"transition","attributes":{"direction":0},"name":"none","objectID":"0"}],"automaticPlay":false,"hyperlinks":[],"accessibility":[{"text":"Our Setup","targetRectangle":{"y":79,"x":99,"width":395.8450003039838,"height":100.53440856933594}},{"text":"proud-touched.gif","targetRectangle":{"y":791.14453125,"x":1289.153564453125,"width":498,"height":273}},{"text":"Circa September 2019","targetRectangle":{"y":180.44745779037476,"x":98.599999904632568,"width":579.59000000000003,"height":66.404617309570312}},{"text":"Almost no Macs were DEP\/ADE","targetRectangle":{"y":338.52792358398438,"x":147,"width":681.84000000000015,"height":55.656005859375}},{"text":"Prepared via MDS; AD-bound admin accounts","targetRectangle":{"y":389.96232167110429,"x":147,"width":994.12799999999993,"height":100.656005859375}},{"text":"Small amount of MDM-enrolled Macs","targetRectangle":{"y":486.39671975822421,"x":147,"width":801.16799999999989,"height":100.656005859375}},{"text":"Data Transfers\/Backup facilitated by IT at time of new device setup\/re-image","targetRectangle":{"y":582.83111784534412,"x":147,"width":1641.1200000000001,"height":100.656005859375}},{"text":"FileVault discouraged","targetRectangle":{"y":679.26551593246404,"x":147,"width":459.60000000000014,"height":100.656005859375}},{"text":"Munki on-prem","targetRectangle":{"y":775.69991401958396,"x":147,"width":327.31200000000001,"height":100.656005859375}},{"text":"Encouraging users to update at time of setup","targetRectangle":{"y":872.13431210670387,"x":147,"width":968.25599999999986,"height":100.656005859375}}],"baseLayer":{"animations":[],"initialState":{"affineTransform":[1,0,0,1,0,0],"masksToBounds":false,"rotation":0,"scale":1,"position":{"pointX":960,"pointY":540},"width":1920,"sublayerTransform":[1,0,0,0,0,1,0,0,0,0,1,0,0,0,0,1],"contentsRect":{"y":0,"x":0,"width":1,"height":1},"opacity":1,"edgeAntialiasingMask":251658240,"height":1080,"hidden":false,"anchorPoint":{"pointX":0.5,"pointY":0.5}},"objectID":"0","layers":[{"animations":[],"initialState":{"affineTransform":[1,0,0,1,0,0],"masksToBounds":false,"rotation":0,"scale":1,"position":{"pointX":960,"pointY":540},"width":1920,"sublayerTransform":[1,0,0,0,0,1,0,0,0,0,1,-0.00035007912466775983,0,0,0,1],"contentsRect":{"y":0,"x":0,"width":1,"height":1},"opacity":1,"edgeAntialiasingMask":251658240,"height":1080,"hidden":false,"anchorPoint":{"pointX":0.5,"pointY":0.5}},"layers":[{"animations":[],"layers":[],"texturedRectangle":{"isBackgroundTexture":false,"singleTextureOpacity":1,"textureType":0,"textBaseline":0,"textXHeight":0,"isVerticalText":false},"initialState":{"affineTransform":[1,0,0,1,0,0],"masksToBounds":false,"rotation":0,"scale":1,"position":{"pointX":960,"pointY":540},"width":1920,"sublayerTransform":[1,0,0,0,0,1,0,0,0,0,1,0,0,0,0,1],"contentsRect":{"y":0,"x":0,"width":1,"height":1},"opacity":1,"edgeAntialiasingMask":0,"height":1080,"hidden":false,"anchorPoint":{"pointX":0.5,"pointY":0.5}},"texture":"414F9E7A00D9B99A6E9BD772362F6ECB"}]}]}}]}